state_machine_operator/__init__.py
state_machine_operator/defaults.py
state_machine_operator/schema.py
state_machine_operator/utils.py
state_machine_operator/analysis/__init__.py
state_machine_operator/analysis/manager.py
state_machine_operator/analysis/plot.py
state_machine_operator/client/__init__.py
state_machine_operator/config/__init__.py
state_machine_operator/config/config.py
state_machine_operator/machine/__init__.py
state_machine_operator/machine/machine.py
state_machine_operator/manager/__init__.py
state_machine_operator/manager/manager.py
state_machine_operator/manager/registry.py
state_machine_operator/manager/utils.py
state_machine_operator/tracker/__init__.py
state_machine_operator/tracker/heartbeat.py
state_machine_operator/tracker/job.py
state_machine_operator/tracker/template.py
state_machine_operator/tracker/tracker.py
state_machine_operator/tracker/types.py
state_machine_operator/tracker/utils.py
state_machine_operator/tracker/watcher.py
state_machine_operator/tracker/flux/__init__.py
state_machine_operator/tracker/flux/event.py
state_machine_operator/tracker/flux/handle.py
state_machine_operator/tracker/flux/job.py
state_machine_operator/tracker/flux/state.py
state_machine_operator/tracker/flux/tracker.py
state_machine_operator/tracker/kubernetes/__init__.py
state_machine_operator/tracker/kubernetes/event.py
state_machine_operator/tracker/kubernetes/job.py
state_machine_operator/tracker/kubernetes/state.py
state_machine_operator/tracker/kubernetes/tracker.py
state_machine_operator-0.0.1.dist-info/METADATA
state_machine_operator-0.0.1.dist-info/WHEEL
state_machine_operator-0.0.1.dist-info/entry_points.txt
state_machine_operator-0.0.1.dist-info/top_level.txt
state_machine_operator-0.0.1.dist-info/RECORD
