Metadata-Version: 2.1
Name: state-machine-operator
Version: 0.0.1
Summary: State Machine orchestrator intended for Kubernetes
Home-page: https://github.com/converged-computing/state-machine-operator
Author: Vanessasaurus
Author-email: vsoch@users.noreply.github.com
Maintainer: Vanessasaurus
License: MIT
Keywords: state machine,simulation,hpc,kubernetes
Classifier: Intended Audience :: Science/Research
Classifier: Intended Audience :: Developers
Classifier: License :: OSI Approved :: Apache Software License
Classifier: Programming Language :: C
Classifier: Programming Language :: Python
Classifier: Topic :: Software Development
Classifier: Topic :: Scientific/Engineering
Classifier: Operating System :: Unix
Classifier: Programming Language :: Python :: 3.11
Requires-Dist: python-statemachine
Requires-Dist: jsonschema
Requires-Dist: Jinja2
Requires-Dist: pyyaml
Requires-Dist: kubernetes
